MANIFEST.in
README.rst
runtests.sh
setup.py
demos/appengine/README
demos/appengine/app.yaml
demos/appengine/blog.py
demos/appengine/static/blog.css
demos/appengine/templates/archive.html
demos/appengine/templates/base.html
demos/appengine/templates/compose.html
demos/appengine/templates/entry.html
demos/appengine/templates/feed.xml
demos/appengine/templates/home.html
demos/appengine/templates/modules/entry.html
demos/auth/authdemo.py
demos/benchmark/benchmark.py
demos/benchmark/chunk_benchmark.py
demos/benchmark/stack_context_benchmark.py
demos/benchmark/template_benchmark.py
demos/blog/README
demos/blog/blog.py
demos/blog/schema.sql
demos/blog/static/blog.css
demos/blog/templates/archive.html
demos/blog/templates/base.html
demos/blog/templates/compose.html
demos/blog/templates/entry.html
demos/blog/templates/feed.xml
demos/blog/templates/home.html
demos/blog/templates/modules/entry.html
demos/chat/chatdemo.py
demos/chat/static/chat.css
demos/chat/static/chat.js
demos/chat/templates/index.html
demos/chat/templates/message.html
demos/facebook/README
demos/facebook/facebook.py
demos/facebook/static/facebook.css
demos/facebook/static/facebook.js
demos/facebook/templates/stream.html
demos/facebook/templates/modules/post.html
demos/helloworld/helloworld.py
demos/s3server/s3server.py
demos/twitter/home.html
demos/twitter/twitterdemo.py
demos/websocket/chatdemo.py
demos/websocket/static/chat.css
demos/websocket/static/chat.js
demos/websocket/templates/index.html
demos/websocket/templates/message.html
tornado/__init__.py
tornado/auth.py
tornado/autoreload.py
tornado/ca-certificates.crt
tornado/concurrent.py
tornado/curl_httpclient.py
tornado/escape.py
tornado/gen.py
tornado/httpclient.py
tornado/httpserver.py
tornado/httputil.py
tornado/ioloop.py
tornado/iostream.py
tornado/locale.py
tornado/log.py
tornado/netutil.py
tornado/options.py
tornado/process.py
tornado/simple_httpclient.py
tornado/speedups.c
tornado/stack_context.py
tornado/tcpserver.py
tornado/template.py
tornado_bedframe.egg-info/PKG-INFO
tornado_bedframe.egg-info/SOURCES.txt
tornado_bedframe.egg-info/dependency_links.txt
tornado_bedframe.egg-info/requires.txt
tornado_bedframe.egg-info/top_level.txt