Metadata-Version: 1.1
Name: tornado-bedframe
Version: 3.2.0
Summary: Tornado is a Python web framework and asynchronous networking library, originally developed at FriendFeed.
Home-page: http://www.tornadoweb.org/
Author: Facebook
Author-email: python-tornado@googlegroups.com
License: http://www.apache.org/licenses/LICENSE-2.0
Platform: UNKNOWN
Classifier: License :: OSI Approved :: Apache Software License
Classifier: Programming Language :: Python :: 2
Classifier: Programming Language :: Python :: 2.6
Classifier: Programming Language :: Python :: 2.7
Classifier: Programming Language :: Python :: 3
Classifier: Programming Language :: Python :: 3.2
Classifier: Programming Language :: Python :: 3.3
Classifier: Programming Language :: Python :: 3.4
Classifier: Programming Language :: Python :: Implementation :: CPython
Classifier: Programming Language :: Python :: Implementation :: PyPy
